tekra/__init__.py
tekra/cli.py
tekra/project.py
tekra-0.1.1.dist-info/LICENSE
tekra-0.1.1.dist-info/METADATA
tekra-0.1.1.dist-info/WHEEL
tekra-0.1.1.dist-info/RECORD
